rvvsuite/__init__.py
rvvsuite/asm/__init__.py
rvvsuite/asm/parser.py
rvvsuite/asm/translator.py
rvvsuite/common/__init__.py
rvvsuite/common/helpers.py
rvvsuite/common/supported_features.py
rvvsuite/rtg/__init__.py
rvvsuite/rtg/confparser.py
rvvsuite/rtg/ga.py
rvvsuite/rtg/init_data_generator.py
rvvsuite/rtg/vrtg.py
rvv_suite-0.0.1.dist-info/LICENSE.txt
rvv_suite-0.0.1.dist-info/METADATA
rvv_suite-0.0.1.dist-info/WHEEL
rvv_suite-0.0.1.dist-info/top_level.txt
rvv_suite-0.0.1.dist-info/RECORD
